inequality/__init__.py
inequality/atkinson.py
inequality/gini.py
inequality/pen.py
inequality/schutz.py
inequality/theil.py
inequality/utils.py
inequality/wolfson.py
inequality/tests/__init__.py
inequality/tests/test_atkinson.py
inequality/tests/test_gini.py
inequality/tests/test_interface.py
inequality/tests/test_pengram.py
inequality/tests/test_schutz.py
inequality/tests/test_theil.py
inequality/tests/test_wolfson.py
inequality-1.1.2.dist-info/licenses/LICENSE.txt
inequality-1.1.2.dist-info/METADATA
inequality-1.1.2.dist-info/WHEEL
inequality-1.1.2.dist-info/top_level.txt
inequality-1.1.2.dist-info/RECORD
