Metadata-Version: 2.4
Name: inequality
Version: 1.1.2
Summary: inequality: Spatial inequality analysis
Author-email: PySAL Developers <pysal-dev@googlegroups.com>
Maintainer: PySAL Developers
License: BSD 3-Clause
Project-URL: Home, https://github.com/pysal/inequality/
Project-URL: Repository, https://github.com/pysal/inequality
Keywords: spatial statistics,spatial inequality
Classifier: Programming Language :: Python :: 3
Classifier: License :: OSI Approved :: BSD License
Classifier: Operating System :: OS Independent
Classifier: Intended Audience :: Science/Research
Classifier: Topic :: Scientific/Engineering :: GIS
Requires-Python: >=3.11
License-File: LICENSE.txt
Requires-Dist: libpysal>=4.12
Requires-Dist: matplotlib>=3.8
Requires-Dist: numpy>=1.26
Requires-Dist: pandas>=2.1
Requires-Dist: scipy>=1.12
Provides-Extra: dev
Requires-Dist: pre-commit; extra == "dev"
Requires-Dist: ruff; extra == "dev"
Provides-Extra: docs
Requires-Dist: nbsphinx; extra == "docs"
Requires-Dist: numpydoc; extra == "docs"
Requires-Dist: sphinx; extra == "docs"
Requires-Dist: sphinxcontrib-bibtex; extra == "docs"
Requires-Dist: sphinx-gallery; extra == "docs"
Requires-Dist: sphinx_bootstrap_theme; extra == "docs"
Requires-Dist: pydata-sphinx-theme; extra == "docs"
Provides-Extra: tests
Requires-Dist: codecov; extra == "tests"
Requires-Dist: folium; extra == "tests"
Requires-Dist: geopandas; extra == "tests"
Requires-Dist: jupyterlab; extra == "tests"
Requires-Dist: mapclassify; extra == "tests"
Requires-Dist: pytest; extra == "tests"
Requires-Dist: pytest-cov; extra == "tests"
Requires-Dist: pytest-xdist; extra == "tests"
Requires-Dist: seaborn; extra == "tests"
Provides-Extra: pen
Requires-Dist: seaborn; extra == "pen"
Dynamic: license-file
